fastapi_auth_starter/__init__.py
fastapi_auth_starter/cli.py
fastapi_auth_starter/templates/.env.example
fastapi_auth_starter/templates/.gitignore
fastapi_auth_starter/templates/README.md
fastapi_auth_starter/templates/alembic.ini
fastapi_auth_starter/templates/pyproject.toml
fastapi_auth_starter/templates/runtime.txt
fastapi_auth_starter/templates/vercel.json
fastapi_auth_starter/templates/alembic/README
fastapi_auth_starter/templates/alembic/env.py
fastapi_auth_starter/templates/alembic/script.py.mako
fastapi_auth_starter/templates/alembic/versions/__init__.py
fastapi_auth_starter/templates/app/__init__.py
fastapi_auth_starter/templates/app/main.py
fastapi_auth_starter/templates/app/api/__init__.py
fastapi_auth_starter/templates/app/api/v1/__init__.py
fastapi_auth_starter/templates/app/api/v1/api.py
fastapi_auth_starter/templates/app/api/v1/routes/__init__.py
fastapi_auth_starter/templates/app/api/v1/routes/auth.py
fastapi_auth_starter/templates/app/api/v1/routes/health.py
fastapi_auth_starter/templates/app/api/v1/routes/task.py
fastapi_auth_starter/templates/app/api/v1/routes/user.py
fastapi_auth_starter/templates/app/api/v1/schemas/__init__.py
fastapi_auth_starter/templates/app/api/v1/schemas/auth.py
fastapi_auth_starter/templates/app/api/v1/schemas/task.py
fastapi_auth_starter/templates/app/api/v1/schemas/user.py
fastapi_auth_starter/templates/app/core/__init__.py
fastapi_auth_starter/templates/app/core/config.py
fastapi_auth_starter/templates/app/core/database.py
fastapi_auth_starter/templates/app/core/dependencies.py
fastapi_auth_starter/templates/app/core/exceptions.py
fastapi_auth_starter/templates/app/db/__init__.py
fastapi_auth_starter/templates/app/models/__init__.py
fastapi_auth_starter/templates/app/models/task.py
fastapi_auth_starter/templates/app/models/user.py
fastapi_auth_starter/templates/app/services/__init__.py
fastapi_auth_starter/templates/app/services/auth.py
fastapi_auth_starter/templates/app/services/task.py
fastapi_auth_starter-1.0.5.dist-info/METADATA
fastapi_auth_starter-1.0.5.dist-info/WHEEL
fastapi_auth_starter-1.0.5.dist-info/entry_points.txt
fastapi_auth_starter-1.0.5.dist-info/RECORD
