Metadata-Version: 2.4
Name: fastapi-auth-starter
Version: 1.0.5
Summary: A clean architecture FastAPI starter template with authentication (WorkOS), PostgreSQL, and Alembic migrations
Project-URL: Homepage, https://github.com/splenwilz/fastapi-auth-starter
Project-URL: Documentation, https://github.com/splenwilz/fastapi-auth-starter#readme
Project-URL: Repository, https://github.com/splenwilz/fastapi-auth-starter
Project-URL: Issues, https://github.com/splenwilz/fastapi-auth-starter/issues
Author-email: Godswill William <godswill.williamsz@gmail.com>
Maintainer-email: Godswill William <godswill.williamsz@gmail.com>
License: MIT
Keywords: alembic,authentication,fastapi,postgresql,starter,template
Classifier: Development Status :: 4 - Beta
Classifier: Framework :: FastAPI
Classifier: Intended Audience :: Developers
Classifier: License :: OSI Approved :: MIT License
Classifier: Programming Language :: Python :: 3
Classifier: Programming Language :: Python :: 3.12
Classifier: Programming Language :: Python :: 3.13
Classifier: Topic :: Internet :: WWW/HTTP :: HTTP Servers
Classifier: Topic :: Software Development :: Libraries :: Python Modules
Requires-Python: >=3.12
Requires-Dist: asyncpg>=0.30.0
Requires-Dist: authlib>=1.6.5
Requires-Dist: fastapi>=0.121.0
Requires-Dist: greenlet>=3.2.4
Requires-Dist: httpx>=0.28.1
Requires-Dist: pydantic-settings>=2.11.0
Requires-Dist: pydantic>=2.0.0
Requires-Dist: sqlalchemy>=2.0.44
Requires-Dist: uvicorn[standard]>=0.38.0
Requires-Dist: workos>=5.0.0
Provides-Extra: dev
Requires-Dist: alembic>=1.17.1; extra == 'dev'
Requires-Dist: psycopg2-binary>=2.9.11; extra == 'dev'
